Metadata-Version: 2.1
Name: trefle
Version: 0.2
Summary: Trefle stands for Trefle is a Revised and Evolutionary-based Fuzzy Logic Engine. It is an implementation of the FuzzyCoCo algorithm i.e. a scikit-learn compatible estimator that use a cooperative coevolution algorithm to find and build interpretable fuzzy systems. Designed for both students and researchers 
Home-page: http://iict-space.heig-vd.ch/cpn/
Author: Gary Marigliano
License: UNKNOWN
Platform: UNKNOWN
Requires-Python: >=3.5
Provides-Extra: evo_plot
Requires-Dist: deap (>=1.2.2)
Requires-Dist: pandas (>=0.22.0)
Requires-Dist: scikit-learn (>=0.19.1)
Requires-Dist: scipy (>=1.0.0)
Requires-Dist: numpy (>=1.14.0)
Requires-Dist: bitarray (==0.8.3)
Provides-Extra: evo_plot
Requires-Dist: matplotlib (>=2.1.1); extra == 'evo_plot'
